README.txt
setup.py
expel/__init__.py
expel.lib.egg-info/PKG-INFO
expel.lib.egg-info/SOURCES.txt
expel.lib.egg-info/dependency_links.txt
expel.lib.egg-info/namespace_packages.txt
expel.lib.egg-info/requires.txt
expel.lib.egg-info/top_level.txt
expel/lib/__init__.py
expel/lib/config.py
expel/lib/event.py
expel/lib/exception.py
expel/lib/filter.py
expel/lib/looper.py
expel/lib/plugin.py
expel/lib/utility.py
expel/lib/xsource.py
expel/lib/reactor/__init__.py
expel/lib/reactor/console.py
expel/lib/support/__init__.py
expel/lib/support/darwin/__init__.py
expel/lib/support/darwin/settings.py
expel/lib/support/darwin/ui.py
expel/lib/support/posix/__init__.py
expel/lib/support/posix/settings.py
expel/lib/support/posix/ui.py
expel/lib/support/win32/__init__.py
expel/lib/support/win32/settings.py
expel/lib/support/win32/ui.py