Metadata-Version: 1.0
Name: expel.lib
Version: 0.2
Summary: Generate and respond to xPL messages.
Home-page: http://www/sffjunkie.co.uk/python-expel.html
Author: Simon Kennedy
Author-email: code@sffjunkie.co.uk
License: Apache-2.0
Platform: UNKNOWN
